LICENCE.txt
MANIFEST.in
PYPI.md
README.md
pyproject.toml
requirements-build.txt
requirements.txt
setup.py
jindr/VERSION
jindr/__init__.py
jindr/docker.py
jindr/exceptions.py
jindr/version.py
jindr.egg-info/PKG-INFO
jindr.egg-info/SOURCES.txt
jindr.egg-info/dependency_links.txt
jindr.egg-info/entry_points.txt
jindr.egg-info/requires.txt
jindr.egg-info/top_level.txt
jindr/cli/__init__.py
jindr/cli/jindr.py
jindr/commands/__common__.py
jindr/commands/__init__.py
jindr/commands/copy_image_to_ecr.py
jindr/commands/copy_image_to_registry.py
jindr/commands/delete_images.py
jindr/commands/delete_repo.py
jindr/commands/garbage_collect.py
jindr/commands/inspect_images.py
jindr/commands/list_images.py
jindr/commands/list_repos.py
jindr/commands/registry_info.py
jindr/commands/registry_restart.py
jindr/commands/registry_start.py
jindr/commands/registry_status.py
jindr/commands/registry_stop.py
jindr/lib/__init__.py
jindr/lib/aws.py
jindr/lib/misc.py