Metadata-Version: 2.1
Name: jindr
Version: 1.5.0
Summary: Manage a local, private docker registry
Home-page: https://github.com/jin-gizmo/jindr
Author: Murray Andrews
License: 3-Clause BSD License
Platform: macOS
Platform: Linux
Classifier: Development Status :: 5 - Production/Stable
Classifier: Environment :: Console
Classifier: Intended Audience :: Developers
Classifier: License :: OSI Approved :: BSD License
Classifier: Natural Language :: English
Classifier: Operating System :: MacOS
Classifier: Operating System :: POSIX :: Linux
Classifier: Programming Language :: Python :: 3 :: Only
Classifier: Topic :: Software Development :: Build Tools
Classifier: Topic :: Utilities
Requires-Python: >=3.11.0
License-File: LICENCE.txt
